odoo8_addon_quality_control_stock-8.0.1.0.1.99.dev37-py3.8-nspkg.pth
odoo_addons/quality_control_stock/README.rst
odoo_addons/quality_control_stock/__init__.py
odoo_addons/quality_control_stock/__openerp__.py
odoo_addons/quality_control_stock/data/quality_control_stock_data.xml
odoo_addons/quality_control_stock/i18n/ca.po
odoo_addons/quality_control_stock/i18n/de.po
odoo_addons/quality_control_stock/i18n/el_GR.po
odoo_addons/quality_control_stock/i18n/es.po
odoo_addons/quality_control_stock/i18n/es_AR.po
odoo_addons/quality_control_stock/i18n/es_ES.po
odoo_addons/quality_control_stock/i18n/es_MX.po
odoo_addons/quality_control_stock/i18n/eu.po
odoo_addons/quality_control_stock/i18n/fi.po
odoo_addons/quality_control_stock/i18n/fr.po
odoo_addons/quality_control_stock/i18n/fr_CH.po
odoo_addons/quality_control_stock/i18n/fr_FR.po
odoo_addons/quality_control_stock/i18n/gl.po
odoo_addons/quality_control_stock/i18n/hr.po
odoo_addons/quality_control_stock/i18n/hr_HR.po
odoo_addons/quality_control_stock/i18n/it.po
odoo_addons/quality_control_stock/i18n/nl.po
odoo_addons/quality_control_stock/i18n/nl_NL.po
odoo_addons/quality_control_stock/i18n/pt.po
odoo_addons/quality_control_stock/i18n/pt_BR.po
odoo_addons/quality_control_stock/i18n/quality_control_stock.pot
odoo_addons/quality_control_stock/i18n/ro.po
odoo_addons/quality_control_stock/i18n/ru.po
odoo_addons/quality_control_stock/i18n/sk.po
odoo_addons/quality_control_stock/i18n/sl.po
odoo_addons/quality_control_stock/i18n/tr.po
odoo_addons/quality_control_stock/i18n/tr_TR.po
odoo_addons/quality_control_stock/i18n/vi_VN.po
odoo_addons/quality_control_stock/i18n/zh_CN.po
odoo_addons/quality_control_stock/models/__init__.py
odoo_addons/quality_control_stock/models/qc_inspection.py
odoo_addons/quality_control_stock/models/qc_trigger.py
odoo_addons/quality_control_stock/models/stock_picking.py
odoo_addons/quality_control_stock/models/stock_picking_type.py
odoo_addons/quality_control_stock/models/stock_production_lot.py
odoo8_addon_quality_control_stock-8.0.1.0.1.99.dev37.dist-info/METADATA
odoo8_addon_quality_control_stock-8.0.1.0.1.99.dev37.dist-info/WHEEL
odoo8_addon_quality_control_stock-8.0.1.0.1.99.dev37.dist-info/namespace_packages.txt
odoo8_addon_quality_control_stock-8.0.1.0.1.99.dev37.dist-info/top_level.txt
odoo8_addon_quality_control_stock-8.0.1.0.1.99.dev37.dist-info/RECORD
